MANIFEST.in
README.rst
requirements.txt
setup.cfg
setup.py
kotti_util/__init__.py
kotti_util/renderers.py
kotti_util/util.py
kotti_util.egg-info/PKG-INFO
kotti_util.egg-info/SOURCES.txt
kotti_util.egg-info/dependency_links.txt
kotti_util.egg-info/not-zip-safe
kotti_util.egg-info/requires.txt
kotti_util.egg-info/top_level.txt
kotti_util/locale/.gitkeep
kotti_util/tests/conftest.py
kotti_util/tests/test_functional.py
kotti_util/tests/test_resources.py
kotti_util/tests/test_view.py
kotti_util/views/__init__.py